optimization_metadata/__init__.py
optimization_metadata/data.py
optimization_metadata/dataset_features.py
optimization_metadata/hypermemory_api.py
optimization_metadata/io_dataframe.py
optimization_metadata/io_dill.py
optimization_metadata/io_helpers.py
optimization_metadata/io_json.py
optimization_metadata/memory_conv.py
optimization_metadata/memory_dump.py
optimization_metadata/memory_io.py
optimization_metadata/memory_load.py
optimization_metadata/paths.py
optimization_metadata/verbosity.py
optimization_metadata/wrappers.py
optimization_metadata/utils/__init__.py
optimization_metadata/utils/path_utils.py
optimization_metadata/utils/utils.py
tests/__init__.py
tests/_test_hyperactive.py
tests/test_convert_dataframe.py
tests/test_dataframe2memory_dict.py
tests/test_hyperactive_wrapper.py
tests/test_memory_dict2dataframe.py
optimization_metadata-0.3.2.dist-info/LICENSE
optimization_metadata-0.3.2.dist-info/METADATA
optimization_metadata-0.3.2.dist-info/WHEEL
optimization_metadata-0.3.2.dist-info/top_level.txt
optimization_metadata-0.3.2.dist-info/RECORD
