Metadata-Version: 2.1
Name: optimization-metadata
Version: 0.3.2
Summary: Meta-data core functionalities for Hyperactive
Home-page: https://github.com/SimonBlanke/Optimization-Metadata
Author: Simon Blanke
Author-email: simon.blanke@yahoo.com
License: MIT
Keywords: visualization,data-science
Platform: UNKNOWN
Classifier: Programming Language :: Python :: 3
Classifier: Programming Language :: Python :: 3.5
Classifier: Programming Language :: Python :: 3.6
Classifier: Programming Language :: Python :: 3.7
Classifier: License :: OSI Approved :: MIT License
Classifier: Operating System :: OS Independent
Classifier: Topic :: Scientific/Engineering :: Information Analysis
Classifier: Topic :: Scientific/Engineering :: Mathematics
Classifier: Topic :: Software Development :: Libraries :: Python Modules
Classifier: Intended Audience :: Developers
Classifier: Intended Audience :: Information Technology
Classifier: Intended Audience :: Science/Research
Requires-Dist: numpy
Requires-Dist: pandas
Requires-Dist: tqdm
Requires-Dist: dill
